image_processing_KB/__init__.py
image_processing_KB/processing/__init__.py
image_processing_KB/processing/functions.py
image_processing_KB/utils/Yiq2Rgb_helping_methods.py
image_processing_KB/utils/__init__.py
image_processing_KB/utils/correlation.py
image_processing_KB/utils/histogram_stretching.py
image_processing_KB/utils/hsb.py
image_processing_KB/utils/kernels.py
image_processing_KB-0.0.3.dist-info/METADATA
image_processing_KB-0.0.3.dist-info/WHEEL
image_processing_KB-0.0.3.dist-info/top_level.txt
image_processing_KB-0.0.3.dist-info/RECORD
