Metadata-Version: 2.1
Name: image-processing-KB
Version: 0.0.3
Summary: This package performs a few image operations like Sobel and Saturation.
Home-page: https://github.com/KelvinBrenand/image-processing-package
Author: Kelvin Brenand
Author-email: brenand.kelvin@gmail.com
Requires-Python: >=3.8
Requires-Dist: numpy
